search_master_regulators/__init__.py
search_master_regulators/main.py
search_master_regulators-1.0.dist-info/METADATA
search_master_regulators-1.0.dist-info/WHEEL
search_master_regulators-1.0.dist-info/entry_points.txt
search_master_regulators-1.0.dist-info/top_level.txt
search_master_regulators-1.0.dist-info/RECORD
